FaceBagNet/1.jpg
FaceBagNet/FaceAnti.py
FaceBagNet/FaceBagNet_base.py
FaceBagNet/FaceBagNet_model_A.py
FaceBagNet/__init__.py
FaceBagNet/__pycache__/FaceBagNet.cpython-36.pyc
FaceBagNet/__pycache__/FaceBagNet_model_A.cpython-36.pyc
FaceBagNet/model/global_min_acer_model.pth
FaceBagNet-0.0.5.dist-info/METADATA
FaceBagNet-0.0.5.dist-info/WHEEL
FaceBagNet-0.0.5.dist-info/top_level.txt
FaceBagNet-0.0.5.dist-info/RECORD
